setup.py
command_line/pngpadder
pngpadder/__init__.py
pngpadder.egg-info/PKG-INFO
pngpadder.egg-info/SOURCES.txt
pngpadder.egg-info/dependency_links.txt
pngpadder.egg-info/top_level.txt