Metadata-Version: 1.1
Name: pngpadder
Version: 0.3
Summary: A tool for padding PNG files to specific sizes
Home-page: https://github.com/dalemyers/pngpadder
Author: Dale Myers
Author-email: dale@myers.io
License: MIT
Keywords: png
Platform: UNKNOWN
Classifier: Development Status :: 3 - Alpha
Classifier: Intended Audience :: Developers
Classifier: Programming Language :: Python :: 2
Classifier: Programming Language :: Python :: 2.7
Classifier: Topic :: Utilities
